{"note":"Don't delete this file! It's used internally to help with page regeneration.","body":"Todo manager with a command-line interface\r\n\r\nAuthor: Xiao Jia <me@xiao-jia.com>\r\n\r\nDependency:\r\n\r\n    ruby (mandatory; please install it using https://rvm.io if possible)\r\n    git  (optional if you don't need to upload TODOs to gist)\r\n\r\nInstallation:\r\n\r\n    gem install highline\r\n    gem install todo_manager\r\n    # Personally, I also make an alias for the executable:\r\n    alias t=todo_manager\r\n\r\nUsage:\r\n\r\n    todo_manager --help\r\n","google":"","name":"Todo manager","tagline":"A simple todo manager gem with a command-line interface. You can also upload your todo items to a git/gist repository."}